dxrpy/__init__.py
dxrpy/client.py
dxrpy/dxr_client.py
dxrpy/datasource/__init__.py
dxrpy/datasource/datasource.py
dxrpy/datasource/types.py
dxrpy/datasource/ingester/__init__.py
dxrpy/datasource/ingester/datasource_ingester.py
dxrpy/index/__init__.py
dxrpy/index/annotators.py
dxrpy/index/index.py
dxrpy/index/json_search_query.py
dxrpy/index/labels.py
dxrpy/index/search_results.py
dxrpy/on_demand_classifier/__init__.py
dxrpy/on_demand_classifier/job.py
dxrpy/on_demand_classifier/on_demand_classifier.py
dxrpy/utils/__init__.py
dxrpy/utils/file_utils.py
dxrpy-0.2.5.dist-info/METADATA
dxrpy-0.2.5.dist-info/WHEEL
dxrpy-0.2.5.dist-info/top_level.txt
dxrpy-0.2.5.dist-info/RECORD
